[
  {
    "id": "section-postpartum",
    "title": "產後衛教",
    "items": [
      { "name": "自然生產產後須知", "link": "https://ihealth.vghtc.gov.tw/media/394" },
      { "name": "剖腹生產產後衛教", "link": "https://ihealth.vghtc.gov.tw/media/427" },
      { "name": "避孕方法介紹", "link": "https://ihealth.vghtc.gov.tw/media/865" },
      { "name": "產後運動", "link": "https://ihealth.vghtc.gov.tw/media/859" },
      { "name": "溫水坐浴", "link": "https://ihealth.vghtc.gov.tw/media/618" },
      { "name": "產後中醫調理", "link": "https://ihealth.vghtc.gov.tw/media/649" },
      { "name": "產後保健手冊", "link": "https://ihealth.vghtc.gov.tw/media/1350" },
      { "name": "哺餵母乳衛教", "link": "https://ihealth.vghtc.gov.tw/media/648" },
      { "name": "揮別黑白哺乳人生", "link": "https://ihealth.vghtc.gov.tw/media/860" }
    ]
  },
  {
    "id": "section-breastfeeding",
    "title": "哺乳專區",
    "items": [
      { "name": "泌乳期乳腺炎護理", "link": "https://ihealth.vghtc.gov.tw/media/621" },
      { "name": "乳腺管阻塞照護", "link": "https://ihealth.vghtc.gov.tw/media/966" },
      { "name": "泌乳期乳房膿瘍術後照護", "link": "https://ihealth.vghtc.gov.tw/media/968" },
      { "name": "奶脹的處理", "link": "https://ihealth.vghtc.gov.tw/media/515" },
      { "name": "怎樣知道您的寶寶有吃飽?", "link": "https://ihealth.vghtc.gov.tw/media/302" },
      { "name": "母乳的儲存與運送", "link": "https://ihealth.vghtc.gov.tw/media/1257" },
      { "name": "母乳哺餵嬰兒的過敏性結腸直腸炎之飲食衛教", "link": "https://ihealth.vghtc.gov.tw/media/1956" }
    ]
  },
  {
    "id": "section-parenting",
    "title": "育兒叮嚀",
    "items": [
      { "name": "貼心叮嚀安心育兒", "link": "https://ihealth.vghtc.gov.tw/media/1334" },
      { "name": "溢吐奶或嗆奶的處理", "link": "https://ihealth.vghtc.gov.tw/media/441" },
      { "name": "認識新生兒黃疸", "link": "https://ihealth.vghtc.gov.tw/media/507" },
      { "name": "認識親子共讀", "link": "https://ihealth.vghtc.gov.tw/media/254" },
      { "name": "認識親子同室", "link": "https://ihealth.vghtc.gov.tw/media/440" },
      { "name": "嬰兒室手冊", "link": "https://ihealth.vghtc.gov.tw/media/1446" },
      { "name": "新生兒紅臀居家照護", "link": "https://ihealth.vghtc.gov.tw/media/1640" },
      { "name": "嬰兒髖關節發育不良之照護", "link": "https://ihealth.vghtc.gov.tw/media/1518" },
      { "name": "兒童預防接種", "link": "https://ihealth.vghtc.gov.tw/media/1520" },
      { "name": "新生兒篩檢及檢查追蹤注意事項", "link": "https://ihealth.vghtc.gov.tw/media/1439" },
      { "name": "新生兒及嬰兒口腔護理(鵝口瘡護理)", "link": "https://ihealth.vghtc.gov.tw/media/479" },
      { "name": "早產兒常見合併症及護理", "link": "https://ihealth.vghtc.gov.tw/media/476" },
      { "name": "一歲以下嬰兒心肺復甦術", "link": "https://ihealth.vghtc.gov.tw/media/518" },
      { "name": "袋鼠式父母照護", "link": "https://ihealth.vghtc.gov.tw/media/416" },
      { "name": "小兒發燒", "link": "https://ihealth.vghtc.gov.tw/media/230" }
    ]
  },
  {
    "id": "section-pelvic",
    "title": "骨盆機能回復",
    "items": [
      { "name": "產後漏尿", "link": "#" },
      { "name": "產後性疼痛", "link": "#" },
      { "name": "產後性生活重建", "link": "#" },
      { "name": "陰道鬆弛與下垂", "link": "#" },
      { "name": "陰道乾澀", "link": "#" },
      { "name": "陰道雷射", "link": "#" },
      { "name": "小陰唇/陰道整型", "link": "#" },
      { "name": "骨盆疼痛與凱格爾運動", "link": "#" }
    ]
  }
]